emrreaper/__init__.py
emrreaper/cli.py
emrreaper-1.0.3.dist-info/DESCRIPTION.rst
emrreaper-1.0.3.dist-info/METADATA
emrreaper-1.0.3.dist-info/RECORD
emrreaper-1.0.3.dist-info/WHEEL
emrreaper-1.0.3.dist-info/entry_points.txt
emrreaper-1.0.3.dist-info/metadata.json
emrreaper-1.0.3.dist-info/top_level.txt
