Metadata-Version: 2.0
Name: emrreaper
Version: 1.0.3
Summary: Enforces emr sla with extreme prejudice!
Home-page: UNKNOWN
Author: Nicholas J
Author-email: nicholas.a.johns5@gmail.com
License: MIT
Keywords: emr
Platform: UNKNOWN
Classifier: Development Status :: 5 - Production/Stable
Classifier: Intended Audience :: Developers
Classifier: License :: OSI Approved :: MIT License
Classifier: Programming Language :: Python :: 2
Classifier: Programming Language :: Python :: 2.7
Classifier: Programming Language :: Python :: 3
Classifier: Programming Language :: Python :: 3.3
Classifier: Programming Language :: Python :: 3.4
Classifier: Programming Language :: Python :: 3.5
Classifier: Programming Language :: Python :: 3.6
Requires-Dist: appdirs (==1.4.3)
Requires-Dist: boto3 (==1.4.4)
Requires-Dist: botocore (==1.5.29)
Requires-Dist: click (==6.7)
Requires-Dist: docutils (==0.13.1)
Requires-Dist: jmespath (==0.9.2)
Requires-Dist: packaging (==16.8)
Requires-Dist: pyparsing (==2.2.0)
Requires-Dist: python-dateutil (==2.6.0)
Requires-Dist: s3transfer (==0.1.10)
Requires-Dist: six (==1.10.0)
